mySelfSumonlymyrailgun.py
mySelfSumonlymyrailgun-1.1.dist-info/METADATA
mySelfSumonlymyrailgun-1.1.dist-info/WHEEL
mySelfSumonlymyrailgun-1.1.dist-info/top_level.txt
mySelfSumonlymyrailgun-1.1.dist-info/RECORD
