Metadata-Version: 2.1
Name: mySelfSumonlymyrailgun
Version: 1.1
Summary: A  module for test
Home-page: https://github.com/vfrtgb158/email
Author: railgun
Author-email: GenshinImpactRailgun@gmail.com
License: MIT
Platform: UNKNOWN
